platelets/__init__.py
platelets/assets.py
platelets-0.5.data/scripts/platelets
platelets-0.5.dist-info/LICENSE
platelets-0.5.dist-info/METADATA
platelets-0.5.dist-info/WHEEL
platelets-0.5.dist-info/top_level.txt
platelets-0.5.dist-info/RECORD
